acrosure_sdk/__init__.py
acrosure_sdk/application.py
acrosure_sdk/client.py
acrosure_sdk/data.py
acrosure_sdk/policy.py
acrosure_sdk/product.py
acrosure_sdk/team.py
acrosure_sdk/version.py
acrosure_sdk/test/__init__.py
acrosure_sdk/test/constants.py
acrosure_sdk/test/test_application.py
acrosure_sdk/test/test_application_flow.py
acrosure_sdk/test/test_application_remaining_endpoints.py
acrosure_sdk/test/test_client.py
acrosure_sdk/test/test_data.py
acrosure_sdk/test/test_policy.py
acrosure_sdk/test/test_product.py
acrosure_sdk/test/test_team.py
acrosure_sdk/utils/__init__.py
acrosure_sdk/utils/api.py
acrosure_sdk/utils/decorate.py
acrosure_sdk/utils/is_python3.py
acrosure_sdk-0.9.2.dist-info/DESCRIPTION.rst
acrosure_sdk-0.9.2.dist-info/METADATA
acrosure_sdk-0.9.2.dist-info/RECORD
acrosure_sdk-0.9.2.dist-info/WHEEL
acrosure_sdk-0.9.2.dist-info/metadata.json
acrosure_sdk-0.9.2.dist-info/top_level.txt
