Metadata-Version: 2.0
Name: acrosure-sdk
Version: 0.9.2
Summary: SDK for Acrosure api
Home-page: https://github.com/jetarin-min/acrosure-py-sdk
Author: Jetarin Chokchaipermpoonphol
Author-email: jetarin.min@gmail.com
License: UNKNOWN
Platform: UNKNOWN
Classifier: Programming Language :: Python :: 3
Classifier: License :: OSI Approved :: MIT License
Classifier: Operating System :: OS Independent
